okx/Account.py
okx/BlockTrading.py
okx/Convert.py
okx/CopyTrading.py
okx/Earning.py
okx/FDBroker.py
okx/Funding.py
okx/Grid.py
okx/MarketData.py
okx/NDBroker.py
okx/PublicData.py
okx/SpreadTrading.py
okx/Status.py
okx/SubAccount.py
okx/Trade.py
okx/TradingData.py
okx/__init__.py
okx/consts.py
okx/exceptions.py
okx/okxclient.py
okx/utils.py
okx/websocket/WebSocketFactory.py
okx/websocket/WsPrivateAsync.py
okx/websocket/WsPublicAsync.py
okx/websocket/WsUtils.py
okx/websocket/__init__.py
test/AccountTest.py
test/BlockTradingTest.py
test/BrokerTest.py
test/ConvertTest.py
test/CopyTradingTest.py
test/EarningTest.py
test/FundingTest.py
test/GridTest.py
test/MarketTest.py
test/PublicDataTest.py
test/SpreadTest.py
test/StackingTest.py
test/SubAccountTest.py
test/TradeTest.py
test/TradingDataTest.py
test/WsPrivateAsyncTest.py
test/WsPublicAsyncTest.py
test/__init__.py
python_okx_async_django-0.2.11.dist-info/METADATA
python_okx_async_django-0.2.11.dist-info/WHEEL
python_okx_async_django-0.2.11.dist-info/top_level.txt
python_okx_async_django-0.2.11.dist-info/RECORD
