Metadata-Version: 2.1
Name: python-okx-async-django
Version: 0.2.11
Summary: Python SDK for OKX async
Home-page: https://okx.com/docs-v5/
Author: djangocc
Author-email: djangonomo@gmail.com
License: UNKNOWN
Platform: UNKNOWN
Classifier: Programming Language :: Python :: 3
Classifier: License :: OSI Approved :: MIT License
Classifier: Operating System :: OS Independent
Requires-Dist: importlib-metadata
Requires-Dist: httpx[http2]
Requires-Dist: httpx[socks]
Requires-Dist: keyring
Requires-Dist: requests
Requires-Dist: Twisted
Requires-Dist: pyOpenSSL
Requires-Dist: websockets
Requires-Dist: orjson
